verify/__init__.py
verify/abc.py
verify/config/__init__.py
verify/core/__init__.py
verify/core/builder.py
verify/core/cache.py
verify/core/errors.py
verify/core/filter.py
verify/core/safe.py
verify/core/storage.py
verify/core/style.py
verify/core/verify.py
verify_python-0.0.2.dist-info/LICENSE
verify_python-0.0.2.dist-info/METADATA
verify_python-0.0.2.dist-info/WHEEL
verify_python-0.0.2.dist-info/top_level.txt
verify_python-0.0.2.dist-info/RECORD
