Metadata-Version: 2.1
Name: verify-python
Version: 0.0.2
Summary: An elegant verification code generator.
Home-page: https://github.com/blackmonkey121/verify
Author: BlackMonkey
Author-email: 3213322480@qq.com
License: GPLv3
Platform: UNKNOWN
Classifier: Programming Language :: Python :: 3
Classifier: License :: OSI Approved :: GNU General Public License v3 (GPLv3)
Classifier: Operating System :: OS Independent
Requires-Python: >=3.3
Requires-Dist: itsdangerous (>=1.1.0)
Requires-Dist: numpy (>=1.11.3)
Requires-Dist: opencv-python (>=3.4)
Requires-Dist: Pillow (>=7.0)
Requires-Dist: rsa (>=4.0)
